{
	"animations": [
		{
			"offsets": [
				180,
				0
			],
			"loop": true,
			"fps": 24,
			"anim": "idle",
			"indices": [],
			"name": "idle"
		},
		{
			"offsets": [
				551,
				200
			],
			"loop": false,
			"fps": 24,
			"anim": "singLEFT",
			"indices": [],
			"name": "left"
		},
		{
			"offsets": [
				95,
				97
			],
			"loop": false,
			"fps": 24,
			"anim": "singRIGHT",
			"indices": [],
			"name": "right"
		},
		{
			"offsets": [
				464,
				116
			],
			"loop": false,
			"fps": 24,
			"anim": "singUP",
			"indices": [],
			"name": "up"
		},
		{
			"offsets": [
				175,
				-63
			],
			"loop": false,
			"fps": 24,
			"anim": "singDOWN",
			"indices": [],
			"name": "down"
		}
	],
	"no_antialiasing": false,
	"image": "characters/Black",
	"position": [
		0,
		0
	],
	"healthicon": "blacksusser",
	"flip_x": false,
	"healthbar_colors": [
		58,
		27,
		79
	],
	"camera_position": [
		-510,
		100
	],
	"sing_duration": 6.1,
	"scale": 1
}